pieuvre/__init__.py
pieuvre/core.py
pieuvre/events.py
pieuvre/exceptions.py
pieuvre/mixins.py
pieuvre/utils.py
pieuvre-0.1.0.dist-info/LICENSE.md
pieuvre-0.1.0.dist-info/METADATA
pieuvre-0.1.0.dist-info/WHEEL
pieuvre-0.1.0.dist-info/top_level.txt
pieuvre-0.1.0.dist-info/RECORD
